Metadata-Version: 2.1
Name: dash_hash
Version: 1.5.1
Summary: Python module for Dash's X11 hashing
Author-email: Pshen Mic <pshenmic@gmail.com>
Project-URL: Homepage, https://github.com/dashpay/dash_hash
Project-URL: Bug Tracker, https://github.com/dashpay/dash_hash/issues
Classifier: Programming Language :: Python :: 3
Classifier: License :: OSI Approved :: MIT License
Classifier: Operating System :: OS Independent
License-File: LICENSE
